isocoder/__init__.py
isocoder/api.py
isocoder/errors.py
isocoder/utils.py
isocoder-0.1.0.dist-info/METADATA
isocoder-0.1.0.dist-info/WHEEL
isocoder-0.1.0.dist-info/top_level.txt
isocoder-0.1.0.dist-info/RECORD
